{ "type": "FeatureCollection",
  "features": [{
    "type": "Feature",
    "geometry": {
      "type": "Point",
      "coordinates": [6.120340,46.311665]
    },
    "properties": {
      "marker-symbol": "marker",
      "circle-color": "orange",
      "title": "11",
      "description": "A border marker"
    }
  }, {
    "type": "Feature",
      "geometry": {
        "type": "Point",
        "coordinates": [6.119653,46.294781]
    },
    "properties": {
      "marker-symbol": "rocket",
      "circle-color": "green",
      "title": "rocket",
      "marker-color": "#bbb"
    }
  }, {
    "type": "Feature",
      "geometry": {
        "type": "Point",
        "coordinates": [6.114712,46.294407]
    },
    "properties": {
      "marker-symbol": "harbor",
      "circle-color": "blue",
      "title": "harbor",
      "marker-color": "#ff8888"
    }
  }]
}
